django_taggit_templatetags2-1.6.0.dist-info/DESCRIPTION.rst
django_taggit_templatetags2-1.6.0.dist-info/LICENSE.txt
django_taggit_templatetags2-1.6.0.dist-info/METADATA
django_taggit_templatetags2-1.6.0.dist-info/RECORD
django_taggit_templatetags2-1.6.0.dist-info/WHEEL
django_taggit_templatetags2-1.6.0.dist-info/metadata.json
django_taggit_templatetags2-1.6.0.dist-info/top_level.txt
taggit_templatetags2/__init__.py
taggit_templatetags2/compat.py
taggit_templatetags2/models.py
taggit_templatetags2/settings.py
taggit_templatetags2/urls.py
taggit_templatetags2/views.py
taggit_templatetags2/static/taggit_templatetags2/js/excanvas.compiled.js
taggit_templatetags2/static/taggit_templatetags2/js/excanvas.js
taggit_templatetags2/static/taggit_templatetags2/js/excanvas_license.txt
taggit_templatetags2/static/taggit_templatetags2/js/tagcanvas.js
taggit_templatetags2/static/taggit_templatetags2/js/tagcanvas.min.js
taggit_templatetags2/templates/taggit_templatetags2/tagcanvas_base.html
taggit_templatetags2/templates/taggit_templatetags2/tagcanvas_include.html
taggit_templatetags2/templates/taggit_templatetags2/tagcanvas_include_js.html
taggit_templatetags2/templates/taggit_templatetags2/tagcanvas_include_js_static.html
taggit_templatetags2/templates/taggit_templatetags2/tagcanvas_list.html
taggit_templatetags2/templates/taggit_templatetags2/tagcanvas_list_item.html
taggit_templatetags2/templates/taggit_templatetags2/tagcloud_include.html
taggit_templatetags2/templates/taggit_templatetags2/taglist_include.html
taggit_templatetags2/templatetags/__init__.py
taggit_templatetags2/templatetags/taggit_templatetags2_tags.py
