Metadata-Version: 2.0
Name: django-taggit-templatetags2
Version: 1.6.0
Summary: Templatetags for django-taggit.
Home-page: https://github.com/fizista/django-taggit-templatetags2
Author: Wojciech Banas
Author-email: fizista@gmail.com
License: BSD
Keywords: django taggit tags tagcloud taglist tagging tag
Platform: UNKNOWN
Classifier: Development Status :: 5 - Production/Stable
Classifier: Programming Language :: Python
Classifier: Programming Language :: Python :: 3
Classifier: Environment :: Web Environment
Classifier: Intended Audience :: Developers
Classifier: License :: OSI Approved :: BSD License
Classifier: Operating System :: OS Independent
Classifier: Framework :: Django
Requires-Dist: django (>=1.5)
Requires-Dist: django-classy-tags (>=0.5.1)
Requires-Dist: django-taggit (>=0.12)
Provides-Extra: test
Requires-Dist: tox (>=1.7); extra == 'test'
